bbhamux.py
bbhamux-0.2.0.dist-info/METADATA
bbhamux-0.2.0.dist-info/WHEEL
bbhamux-0.2.0.dist-info/RECORD
