Metadata-Version: 2.1
Name: bbhamux
Version: 0.2.0
Summary: Minimal library to construct Hierarchical Associative Memories
License: Apache 2.0
Author: Ben Hoover
Author-email: benhoover34@gmail.com
Requires-Python: >=3.10,<4.0
Classifier: License :: Other/Proprietary License
Classifier: Programming Language :: Python :: 3
Classifier: Programming Language :: Python :: 3.10
Classifier: Programming Language :: Python :: 3.11
Classifier: Programming Language :: Python :: 3.12
Requires-Dist: equinox (>=0.11.2,<0.12.0)
Requires-Dist: jax (>=0.4.14,<0.5.0)
Requires-Dist: jaxtyping (>=0.2.25,<0.3.0)
